{
  "id": "gods",
  "schemaVersion": 3,
  "tableType": "meaning-table",
  "categoryId": "supernatural-magic",
  "defaultLanguage": "en",
  "displayName": "Gods",
  "displayNameTranslations": {
    "pt": "Deuses",
    "en": "Gods"
  },
  "description": "A table of descriptive words for deities and divine beings",
  "descriptionTranslations": {
    "en": "A table of descriptive words for deities and divine beings"
  },
  "isPremium": false,
  "isBuiltIn": true,
  "isUserCreated": false,
  "source": "Mythic GME 2e core rulebook",
  "tags": [
    "general"
  ],
  "entries": [
    {
      "range": [
        1,
        1
      ],
      "result": "Active",
      "resultTranslations": {
        "pt": "Ativo",
        "en": "Active"
      },
      "weight": 1,
      "entryRollOn": [],
      "tags": [],
      "disabled": false
    },
    {
      "range": [
        2,
        2
      ],
      "result": "Alien",
      "resultTranslations": {
        "pt": "Alienígena",
        "en": "Alien"
      },
      "weight": 1,
      "entryRollOn": [],
      "tags": [],
      "disabled": false
    },
    {
      "range": [
        3,
        3
      ],
      "result": "Ancient",
      "resultTranslations": {
        "pt": "Ancestral",
        "en": "Ancient"
      },
      "weight": 1,
      "entryRollOn": [],
      "tags": [],
      "disabled": false
    },
    {
      "range": [
        4,
        4
      ],
      "result": "Angelic",
      "resultTranslations": {
        "pt": "Angelical",
        "en": "Angelic"
      },
      "weight": 1,
      "entryRollOn": [],
      "tags": [],
      "disabled": false
    },
    {
      "range": [
        5,
        5
      ],
      "result": "Angry",
      "resultTranslations": {
        "pt": "Irritado",
        "en": "Angry"
      },
      "weight": 1,
      "entryRollOn": [],
      "tags": [],
      "disabled": false
    },
    {
      "range": [
        6,
        6
      ],
      "result": "Animal",
      "resultTranslations": {
        "pt": "Animal",
        "en": "Animal"
      },
      "weight": 1,
      "entryRollOn": [],
      "tags": [],
      "disabled": false
    },
    {
      "range": [
        7,
        7
      ],
      "result": "Art",
      "resultTranslations": {
        "pt": "Arte",
        "en": "Art"
      },
      "weight": 1,
      "entryRollOn": [],
      "tags": [],
      "disabled": false
    },
    {
      "range": [
        8,
        8
      ],
      "result": "Assist",
      "resultTranslations": {
        "pt": "Auxiliar",
        "en": "Assist"
      },
      "weight": 1,
      "entryRollOn": [],
      "tags": [],
      "disabled": false
    },
    {
      "range": [
        9,
        9
      ],
      "result": "Attract",
      "resultTranslations": {
        "pt": "Atrair",
        "en": "Attract"
      },
      "weight": 1,
      "entryRollOn": [],
      "tags": [],
      "disabled": false
    },
    {
      "range": [
        10,
        10
      ],
      "result": "Beautiful",
      "resultTranslations": {
        "pt": "Belo",
        "en": "Beautiful"
      },
      "weight": 1,
      "entryRollOn": [],
      "tags": [],
      "disabled": false
    },
    {
      "range": [
        11,
        11
      ],
      "result": "Bestow",
      "resultTranslations": {
        "pt": "Conceder",
        "en": "Bestow"
      },
      "weight": 1,
      "entryRollOn": [],
      "tags": [],
      "disabled": false
    },
    {
      "range": [
        12,
        12
      ],
      "result": "Betray",
      "resultTranslations": {
        "pt": "Trair",
        "en": "Betray"
      },
      "weight": 1,
      "entryRollOn": [],
      "tags": [],
      "disabled": false
    },
    {
      "range": [
        13,
        13
      ],
      "result": "Bizarre",
      "resultTranslations": {
        "pt": "Bizarro",
        "en": "Bizarre"
      },
      "weight": 1,
      "entryRollOn": [],
      "tags": [],
      "disabled": false
    },
    {
      "range": [
        14,
        14
      ],
      "result": "Capricious",
      "resultTranslations": {
        "pt": "Excêntrico",
        "en": "Capricious"
      },
      "weight": 1,
      "entryRollOn": [],
      "tags": [],
      "disabled": false
    },
    {
      "range": [
        15,
        15
      ],
      "result": "Colorful",
      "resultTranslations": {
        "pt": "Colorido",
        "en": "Colorful"
      },
      "weight": 1,
      "entryRollOn": [],
      "tags": [],
      "disabled": false
    },
    {
      "range": [
        16,
        16
      ],
      "result": "Combat",
      "resultTranslations": {
        "pt": "Combate",
        "en": "Combat"
      },
      "weight": 1,
      "entryRollOn": [],
      "tags": [],
      "disabled": false
    },
    {
      "range": [
        17,
        17
      ],
      "result": "Communicate",
      "resultTranslations": {
        "pt": "Comunicar",
        "en": "Communicate"
      },
      "weight": 1,
      "entryRollOn": [],
      "tags": [],
      "disabled": false
    },
    {
      "range": [
        18,
        18
      ],
      "result": "Conflict",
      "resultTranslations": {
        "pt": "Conflito",
        "en": "Conflict"
      },
      "weight": 1,
      "entryRollOn": [],
      "tags": [],
      "disabled": false
    },
    {
      "range": [
        19,
        19
      ],
      "result": "Control",
      "resultTranslations": {
        "pt": "Controlar",
        "en": "Control"
      },
      "weight": 1,
      "entryRollOn": [],
      "tags": [],
      "disabled": false
    },
    {
      "range": [
        20,
        20
      ],
      "result": "Corruption",
      "resultTranslations": {
        "pt": "Corrupção",
        "en": "Corruption"
      },
      "weight": 1,
      "entryRollOn": [],
      "tags": [],
      "disabled": false
    },
    {
      "range": [
        21,
        21
      ],
      "result": "Cosmic",
      "resultTranslations": {
        "pt": "Cósmico",
        "en": "Cosmic"
      },
      "weight": 1,
      "entryRollOn": [],
      "tags": [],
      "disabled": false
    },
    {
      "range": [
        22,
        22
      ],
      "result": "Create",
      "resultTranslations": {
        "pt": "Criar",
        "en": "Create"
      },
      "weight": 1,
      "entryRollOn": [],
      "tags": [],
      "disabled": false
    },
    {
      "range": [
        23,
        23
      ],
      "result": "Creepy",
      "resultTranslations": {
        "pt": "Tenebroso",
        "en": "Creepy"
      },
      "weight": 1,
      "entryRollOn": [],
      "tags": [],
      "disabled": false
    },
    {
      "range": [
        24,
        24
      ],
      "result": "Cruel",
      "resultTranslations": {
        "pt": "Cruel",
        "en": "Cruel"
      },
      "weight": 1,
      "entryRollOn": [],
      "tags": [],
      "disabled": false
    },
    {
      "range": [
        25,
        25
      ],
      "result": "Cult",
      "resultTranslations": {
        "pt": "Seita",
        "en": "Cult"
      },
      "weight": 1,
      "entryRollOn": [],
      "tags": [],
      "disabled": false
    },
    {
      "range": [
        26,
        26
      ],
      "result": "Dangerous",
      "resultTranslations": {
        "pt": "Perigoso",
        "en": "Dangerous"
      },
      "weight": 1,
      "entryRollOn": [],
      "tags": [],
      "disabled": false
    },
    {
      "range": [
        27,
        27
      ],
      "result": "Dark",
      "resultTranslations": {
        "pt": "Escuro",
        "en": "Dark"
      },
      "weight": 1,
      "entryRollOn": [],
      "tags": [],
      "disabled": false
    },
    {
      "range": [
        28,
        28
      ],
      "result": "Death",
      "resultTranslations": {
        "pt": "Morte",
        "en": "Death"
      },
      "weight": 1,
      "entryRollOn": [],
      "tags": [],
      "disabled": false
    },
    {
      "range": [
        29,
        29
      ],
      "result": "Deceit",
      "resultTranslations": {
        "pt": "Enganar",
        "en": "Deceit"
      },
      "weight": 1,
      "entryRollOn": [],
      "tags": [],
      "disabled": false
    },
    {
      "range": [
        30,
        30
      ],
      "result": "Destroyer",
      "resultTranslations": {
        "pt": "Destruidor",
        "en": "Destroyer"
      },
      "weight": 1,
      "entryRollOn": [],
      "tags": [],
      "disabled": false
    },
    {
      "range": [
        31,
        31
      ],
      "result": "Disgusting",
      "resultTranslations": {
        "pt": "Repugnante",
        "en": "Disgusting"
      },
      "weight": 1,
      "entryRollOn": [],
      "tags": [],
      "disabled": false
    },
    {
      "range": [
        32,
        32
      ],
      "result": "Dominate",
      "resultTranslations": {
        "pt": "Dominar",
        "en": "Dominate"
      },
      "weight": 1,
      "entryRollOn": [],
      "tags": [],
      "disabled": false
    },
    {
      "range": [
        33,
        33
      ],
      "result": "Dreams",
      "resultTranslations": {
        "pt": "Sonhos",
        "en": "Dreams"
      },
      "weight": 1,
      "entryRollOn": [],
      "tags": [],
      "disabled": false
    },
    {
      "range": [
        34,
        34
      ],
      "result": "Elements",
      "resultTranslations": {
        "pt": "Elementos",
        "en": "Elements"
      },
      "weight": 1,
      "entryRollOn": [],
      "tags": [],
      "disabled": false
    },
    {
      "range": [
        35,
        35
      ],
      "result": "Emotions",
      "resultTranslations": {
        "pt": "Emoções",
        "en": "Emotions"
      },
      "weight": 1,
      "entryRollOn": [],
      "tags": [],
      "disabled": false
    },
    {
      "range": [
        36,
        36
      ],
      "result": "Enemies",
      "resultTranslations": {
        "pt": "Inimigos",
        "en": "Enemies"
      },
      "weight": 1,
      "entryRollOn": [],
      "tags": [],
      "disabled": false
    },
    {
      "range": [
        37,
        37
      ],
      "result": "Energy",
      "resultTranslations": {
        "pt": "Energia",
        "en": "Energy"
      },
      "weight": 1,
      "entryRollOn": [],
      "tags": [],
      "disabled": false
    },
    {
      "range": [
        38,
        38
      ],
      "result": "Enormous",
      "resultTranslations": {
        "pt": "Enorme",
        "en": "Enormous"
      },
      "weight": 1,
      "entryRollOn": [],
      "tags": [],
      "disabled": false
    },
    {
      "range": [
        39,
        39
      ],
      "result": "Evil",
      "resultTranslations": {
        "pt": "Mal",
        "en": "Evil"
      },
      "weight": 1,
      "entryRollOn": [],
      "tags": [],
      "disabled": false
    },
    {
      "range": [
        40,
        40
      ],
      "result": "Feminine",
      "resultTranslations": {
        "pt": "Feminino",
        "en": "Feminine"
      },
      "weight": 1,
      "entryRollOn": [],
      "tags": [],
      "disabled": false
    },
    {
      "range": [
        41,
        41
      ],
      "result": "Fallen",
      "resultTranslations": {
        "pt": "Caído",
        "en": "Fallen"
      },
      "weight": 1,
      "entryRollOn": [],
      "tags": [],
      "disabled": false
    },
    {
      "range": [
        42,
        42
      ],
      "result": "Fear",
      "resultTranslations": {
        "pt": "Medo",
        "en": "Fear"
      },
      "weight": 1,
      "entryRollOn": [],
      "tags": [],
      "disabled": false
    },
    {
      "range": [
        43,
        43
      ],
      "result": "Fertility",
      "resultTranslations": {
        "pt": "Fertilidade",
        "en": "Fertility"
      },
      "weight": 1,
      "entryRollOn": [],
      "tags": [],
      "disabled": false
    },
    {
      "range": [
        44,
        44
      ],
      "result": "Festive",
      "resultTranslations": {
        "pt": "Festivo",
        "en": "Festive"
      },
      "weight": 1,
      "entryRollOn": [],
      "tags": [],
      "disabled": false
    },
    {
      "range": [
        45,
        45
      ],
      "result": "Fire",
      "resultTranslations": {
        "pt": "Fogo",
        "en": "Fire"
      },
      "weight": 1,
      "entryRollOn": [],
      "tags": [],
      "disabled": false
    },
    {
      "range": [
        46,
        46
      ],
      "result": "Frightening",
      "resultTranslations": {
        "pt": "Amedrontador",
        "en": "Frightening"
      },
      "weight": 1,
      "entryRollOn": [],
      "tags": [],
      "disabled": false
    },
    {
      "range": [
        47,
        47
      ],
      "result": "Generous",
      "resultTranslations": {
        "pt": "Generoso",
        "en": "Generous"
      },
      "weight": 1,
      "entryRollOn": [],
      "tags": [],
      "disabled": false
    },
    {
      "range": [
        48,
        48
      ],
      "result": "Gentle",
      "resultTranslations": {
        "pt": "Gentil",
        "en": "Gentle"
      },
      "weight": 1,
      "entryRollOn": [],
      "tags": [],
      "disabled": false
    },
    {
      "range": [
        49,
        49
      ],
      "result": "Gifts",
      "resultTranslations": {
        "pt": "Presentes",
        "en": "Gifts"
      },
      "weight": 1,
      "entryRollOn": [],
      "tags": [],
      "disabled": false
    },
    {
      "range": [
        50,
        50
      ],
      "result": "Glorious",
      "resultTranslations": {
        "pt": "Glorioso",
        "en": "Glorious"
      },
      "weight": 1,
      "entryRollOn": [],
      "tags": [],
      "disabled": false
    },
    {
      "range": [
        51,
        51
      ],
      "result": "Good",
      "resultTranslations": {
        "pt": "Bem",
        "en": "Good"
      },
      "weight": 1,
      "entryRollOn": [],
      "tags": [],
      "disabled": false
    },
    {
      "range": [
        52,
        52
      ],
      "result": "Guide",
      "resultTranslations": {
        "pt": "Guiar",
        "en": "Guide"
      },
      "weight": 1,
      "entryRollOn": [],
      "tags": [],
      "disabled": false
    },
    {
      "range": [
        53,
        53
      ],
      "result": "Harm",
      "resultTranslations": {
        "pt": "Prejudicar",
        "en": "Harm"
      },
      "weight": 1,
      "entryRollOn": [],
      "tags": [],
      "disabled": false
    },
    {
      "range": [
        54,
        54
      ],
      "result": "Harsh",
      "resultTranslations": {
        "pt": "Brusco",
        "en": "Harsh"
      },
      "weight": 1,
      "entryRollOn": [],
      "tags": [],
      "disabled": false
    },
    {
      "range": [
        55,
        55
      ],
      "result": "Heal",
      "resultTranslations": {
        "pt": "Curar",
        "en": "Heal"
      },
      "weight": 1,
      "entryRollOn": [],
      "tags": [],
      "disabled": false
    },
    {
      "range": [
        56,
        56
      ],
      "result": "Humanoid",
      "resultTranslations": {
        "pt": "Humanoide",
        "en": "Humanoid"
      },
      "weight": 1,
      "entryRollOn": [],
      "tags": [],
      "disabled": false
    },
    {
      "range": [
        57,
        57
      ],
      "result": "Illness",
      "resultTranslations": {
        "pt": "Doença",
        "en": "Illness"
      },
      "weight": 1,
      "entryRollOn": [],
      "tags": [],
      "disabled": false
    },
    {
      "range": [
        58,
        58
      ],
      "result": "Imprison",
      "resultTranslations": {
        "pt": "Aprisionar",
        "en": "Imprison"
      },
      "weight": 1,
      "entryRollOn": [],
      "tags": [],
      "disabled": false
    },
    {
      "range": [
        59,
        59
      ],
      "result": "Increase",
      "resultTranslations": {
        "pt": "Aumento",
        "en": "Increase"
      },
      "weight": 1,
      "entryRollOn": [],
      "tags": [],
      "disabled": false
    },
    {
      "range": [
        60,
        60
      ],
      "result": "Jealous",
      "resultTranslations": {
        "pt": "Ciumento",
        "en": "Jealous"
      },
      "weight": 1,
      "entryRollOn": [],
      "tags": [],
      "disabled": false
    },
    {
      "range": [
        61,
        61
      ],
      "result": "Justice",
      "resultTranslations": {
        "pt": "Justiça",
        "en": "Justice"
      },
      "weight": 1,
      "entryRollOn": [],
      "tags": [],
      "disabled": false
    },
    {
      "range": [
        62,
        62
      ],
      "result": "Knowledge",
      "resultTranslations": {
        "pt": "Conhecimento",
        "en": "Knowledge"
      },
      "weight": 1,
      "entryRollOn": [],
      "tags": [],
      "disabled": false
    },
    {
      "range": [
        63,
        63
      ],
      "result": "Liberty",
      "resultTranslations": {
        "pt": "Liberdade",
        "en": "Liberty"
      },
      "weight": 1,
      "entryRollOn": [],
      "tags": [],
      "disabled": false
    },
    {
      "range": [
        64,
        64
      ],
      "result": "Life",
      "resultTranslations": {
        "pt": "Vida",
        "en": "Life"
      },
      "weight": 1,
      "entryRollOn": [],
      "tags": [],
      "disabled": false
    },
    {
      "range": [
        65,
        65
      ],
      "result": "Light",
      "resultTranslations": {
        "pt": "Luz",
        "en": "Light"
      },
      "weight": 1,
      "entryRollOn": [],
      "tags": [],
      "disabled": false
    },
    {
      "range": [
        66,
        66
      ],
      "result": "Love",
      "resultTranslations": {
        "pt": "Amor",
        "en": "Love"
      },
      "weight": 1,
      "entryRollOn": [],
      "tags": [],
      "disabled": false
    },
    {
      "range": [
        67,
        67
      ],
      "result": "Magic",
      "resultTranslations": {
        "pt": "Magia",
        "en": "Magic"
      },
      "weight": 1,
      "entryRollOn": [],
      "tags": [],
      "disabled": false
    },
    {
      "range": [
        68,
        68
      ],
      "result": "Majestic",
      "resultTranslations": {
        "pt": "Majestoso",
        "en": "Majestic"
      },
      "weight": 1,
      "entryRollOn": [],
      "tags": [],
      "disabled": false
    },
    {
      "range": [
        69,
        69
      ],
      "result": "Major",
      "resultTranslations": {
        "pt": "Maior",
        "en": "Major"
      },
      "weight": 1,
      "entryRollOn": [],
      "tags": [],
      "disabled": false
    },
    {
      "range": [
        70,
        70
      ],
      "result": "Malice",
      "resultTranslations": {
        "pt": "Malícia",
        "en": "Malice"
      },
      "weight": 1,
      "entryRollOn": [],
      "tags": [],
      "disabled": false
    },
    {
      "range": [
        71,
        71
      ],
      "result": "Masculine",
      "resultTranslations": {
        "pt": "Masculino",
        "en": "Masculine"
      },
      "weight": 1,
      "entryRollOn": [],
      "tags": [],
      "disabled": false
    },
    {
      "range": [
        72,
        72
      ],
      "result": "Mighty",
      "resultTranslations": {
        "pt": "Possante",
        "en": "Mighty"
      },
      "weight": 1,
      "entryRollOn": [],
      "tags": [],
      "disabled": false
    },
    {
      "range": [
        73,
        73
      ],
      "result": "Military",
      "resultTranslations": {
        "pt": "Militar",
        "en": "Military"
      },
      "weight": 1,
      "entryRollOn": [],
      "tags": [],
      "disabled": false
    },
    {
      "range": [
        74,
        74
      ],
      "result": "Minor",
      "resultTranslations": {
        "pt": "Menor",
        "en": "Minor"
      },
      "weight": 1,
      "entryRollOn": [],
      "tags": [],
      "disabled": false
    },
    {
      "range": [
        75,
        75
      ],
      "result": "Monstrous",
      "resultTranslations": {
        "pt": "Monstruoso",
        "en": "Monstrous"
      },
      "weight": 1,
      "entryRollOn": [],
      "tags": [],
      "disabled": false
    },
    {
      "range": [
        76,
        76
      ],
      "result": "Mundane",
      "resultTranslations": {
        "pt": "Mundano",
        "en": "Mundane"
      },
      "weight": 1,
      "entryRollOn": [],
      "tags": [],
      "disabled": false
    },
    {
      "range": [
        77,
        77
      ],
      "result": "Mysterious",
      "resultTranslations": {
        "pt": "Misterioso",
        "en": "Mysterious"
      },
      "weight": 1,
      "entryRollOn": [],
      "tags": [],
      "disabled": false
    },
    {
      "range": [
        78,
        78
      ],
      "result": "Nature",
      "resultTranslations": {
        "pt": "Natureza",
        "en": "Nature"
      },
      "weight": 1,
      "entryRollOn": [],
      "tags": [],
      "disabled": false
    },
    {
      "range": [
        79,
        79
      ],
      "result": "Night",
      "resultTranslations": {
        "pt": "Noite",
        "en": "Night"
      },
      "weight": 1,
      "entryRollOn": [],
      "tags": [],
      "disabled": false
    },
    {
      "range": [
        80,
        80
      ],
      "result": "Oppress",
      "resultTranslations": {
        "pt": "Oprimir",
        "en": "Oppress"
      },
      "weight": 1,
      "entryRollOn": [],
      "tags": [],
      "disabled": false
    },
    {
      "range": [
        81,
        81
      ],
      "result": "Pleasures",
      "resultTranslations": {
        "pt": "Prazeres",
        "en": "Pleasures"
      },
      "weight": 1,
      "entryRollOn": [],
      "tags": [],
      "disabled": false
    },
    {
      "range": [
        82,
        82
      ],
      "result": "Power",
      "resultTranslations": {
        "pt": "Poder",
        "en": "Power"
      },
      "weight": 1,
      "entryRollOn": [],
      "tags": [],
      "disabled": false
    },
    {
      "range": [
        83,
        83
      ],
      "result": "Protector",
      "resultTranslations": {
        "pt": "Protetor",
        "en": "Protector"
      },
      "weight": 1,
      "entryRollOn": [],
      "tags": [],
      "disabled": false
    },
    {
      "range": [
        84,
        84
      ],
      "result": "Punish",
      "resultTranslations": {
        "pt": "Punir",
        "en": "Punish"
      },
      "weight": 1,
      "entryRollOn": [],
      "tags": [],
      "disabled": false
    },
    {
      "range": [
        85,
        85
      ],
      "result": "Ruler",
      "resultTranslations": {
        "pt": "Governante",
        "en": "Ruler"
      },
      "weight": 1,
      "entryRollOn": [],
      "tags": [],
      "disabled": false
    },
    {
      "range": [
        86,
        86
      ],
      "result": "Sacrifice",
      "resultTranslations": {
        "pt": "Sacrificar",
        "en": "Sacrifice"
      },
      "weight": 1,
      "entryRollOn": [],
      "tags": [],
      "disabled": false
    },
    {
      "range": [
        87,
        87
      ],
      "result": "Strange",
      "resultTranslations": {
        "pt": "Estranhar",
        "en": "Strange"
      },
      "weight": 1,
      "entryRollOn": [],
      "tags": [],
      "disabled": false
    },
    {
      "range": [
        88,
        88
      ],
      "result": "Strong",
      "resultTranslations": {
        "pt": "Forte",
        "en": "Strong"
      },
      "weight": 1,
      "entryRollOn": [],
      "tags": [],
      "disabled": false
    },
    {
      "range": [
        89,
        89
      ],
      "result": "Suppress",
      "resultTranslations": {
        "pt": "Suprimir",
        "en": "Suppress"
      },
      "weight": 1,
      "entryRollOn": [],
      "tags": [],
      "disabled": false
    },
    {
      "range": [
        90,
        90
      ],
      "result": "Threatening",
      "resultTranslations": {
        "pt": "Ameaçador",
        "en": "Threatening"
      },
      "weight": 1,
      "entryRollOn": [],
      "tags": [],
      "disabled": false
    },
    {
      "range": [
        91,
        91
      ],
      "result": "Transform",
      "resultTranslations": {
        "pt": "Transformar",
        "en": "Transform"
      },
      "weight": 1,
      "entryRollOn": [],
      "tags": [],
      "disabled": false
    },
    {
      "range": [
        92,
        92
      ],
      "result": "Underworld",
      "resultTranslations": {
        "pt": "Submundo",
        "en": "Underworld"
      },
      "weight": 1,
      "entryRollOn": [],
      "tags": [],
      "disabled": false
    },
    {
      "range": [
        93,
        93
      ],
      "result": "Violent",
      "resultTranslations": {
        "pt": "Violento",
        "en": "Violent"
      },
      "weight": 1,
      "entryRollOn": [],
      "tags": [],
      "disabled": false
    },
    {
      "range": [
        94,
        94
      ],
      "result": "War",
      "resultTranslations": {
        "pt": "Guerra",
        "en": "War"
      },
      "weight": 1,
      "entryRollOn": [],
      "tags": [],
      "disabled": false
    },
    {
      "range": [
        95,
        95
      ],
      "result": "Warm",
      "resultTranslations": {
        "pt": "Caloroso",
        "en": "Warm"
      },
      "weight": 1,
      "entryRollOn": [],
      "tags": [],
      "disabled": false
    },
    {
      "range": [
        96,
        96
      ],
      "result": "Water",
      "resultTranslations": {
        "pt": "Água",
        "en": "Water"
      },
      "weight": 1,
      "entryRollOn": [],
      "tags": [],
      "disabled": false
    },
    {
      "range": [
        97,
        97
      ],
      "result": "Weak",
      "resultTranslations": {
        "pt": "Fraco",
        "en": "Weak"
      },
      "weight": 1,
      "entryRollOn": [],
      "tags": [],
      "disabled": false
    },
    {
      "range": [
        98,
        98
      ],
      "result": "Weapon",
      "resultTranslations": {
        "pt": "Arma",
        "en": "Weapon"
      },
      "weight": 1,
      "entryRollOn": [],
      "tags": [],
      "disabled": false
    },
    {
      "range": [
        99,
        99
      ],
      "result": "Weather",
      "resultTranslations": {
        "pt": "Clima",
        "en": "Weather"
      },
      "weight": 1,
      "entryRollOn": [],
      "tags": [],
      "disabled": false
    },
    {
      "range": [
        100,
        100
      ],
      "result": "Worshiped",
      "resultTranslations": {
        "pt": "Venerado",
        "en": "Worshiped"
      },
      "weight": 1,
      "entryRollOn": [],
      "tags": [],
      "disabled": false
    }
  ],
  "rangeStart": 1,
  "rangeEnd": 100,
  "tableRollOn": [],
  "replacement": false,
  "displayRoll": true
}
