{
  "id": "puzzle_rewards",
  "schemaVersion": 3,
  "tableType": "meaning-table",
  "categoryId": "adventure-elements",
  "defaultLanguage": "en",
  "displayName": "Puzzle Rewards",
  "displayNameTranslations": {
    "pt": "Recompensas de Quebra-cabeça",
    "en": "Puzzle Rewards"
  },
  "description": "Potential rewards and benefits from successfully solving puzzles",
  "descriptionTranslations": {
    "en": "Potential rewards and benefits from successfully solving puzzles"
  },
  "isPremium": true,
  "isBuiltIn": true,
  "isUserCreated": false,
  "source": "Mythic Magazine 44",
  "tags": [
    "premium"
  ],
  "entries": [
    {
      "range": [
        1,
        1
      ],
      "result": "Access",
      "resultTranslations": {
        "pt": "Acessar",
        "en": "Access"
      },
      "weight": 1,
      "entryRollOn": [],
      "tags": [],
      "disabled": false
    },
    {
      "range": [
        2,
        2
      ],
      "result": "Advice",
      "resultTranslations": {
        "pt": "Conselho",
        "en": "Advice"
      },
      "weight": 1,
      "entryRollOn": [],
      "tags": [],
      "disabled": false
    },
    {
      "range": [
        3,
        3
      ],
      "result": "Aid",
      "resultTranslations": {
        "pt": "Auxílio",
        "en": "Aid"
      },
      "weight": 1,
      "entryRollOn": [],
      "tags": [],
      "disabled": false
    },
    {
      "range": [
        4,
        4
      ],
      "result": "Allies",
      "resultTranslations": {
        "pt": "Aliados",
        "en": "Allies"
      },
      "weight": 1,
      "entryRollOn": [],
      "tags": [],
      "disabled": false
    },
    {
      "range": [
        5,
        5
      ],
      "result": "Answers",
      "resultTranslations": {
        "pt": "Respostas",
        "en": "Answers"
      },
      "weight": 1,
      "entryRollOn": [],
      "tags": [],
      "disabled": false
    },
    {
      "range": [
        6,
        6
      ],
      "result": "Art",
      "resultTranslations": {
        "pt": "Arte",
        "en": "Art"
      },
      "weight": 1,
      "entryRollOn": [],
      "tags": [],
      "disabled": false
    },
    {
      "range": [
        7,
        7
      ],
      "result": "Assist",
      "resultTranslations": {
        "pt": "Auxiliar",
        "en": "Assist"
      },
      "weight": 1,
      "entryRollOn": [],
      "tags": [],
      "disabled": false
    },
    {
      "range": [
        8,
        8
      ],
      "result": "Attain",
      "resultTranslations": {
        "pt": "Realizar",
        "en": "Attain"
      },
      "weight": 1,
      "entryRollOn": [],
      "tags": [],
      "disabled": false
    },
    {
      "range": [
        9,
        9
      ],
      "result": "Attract",
      "resultTranslations": {
        "pt": "Atrair",
        "en": "Attract"
      },
      "weight": 1,
      "entryRollOn": [],
      "tags": [],
      "disabled": false
    },
    {
      "range": [
        10,
        10
      ],
      "result": "Befriend",
      "resultTranslations": {
        "pt": "Aliar",
        "en": "Befriend"
      },
      "weight": 1,
      "entryRollOn": [],
      "tags": [],
      "disabled": false
    },
    {
      "range": [
        11,
        11
      ],
      "result": "Benefits",
      "resultTranslations": {
        "pt": "Benefícios",
        "en": "Benefits"
      },
      "weight": 1,
      "entryRollOn": [],
      "tags": [],
      "disabled": false
    },
    {
      "range": [
        12,
        12
      ],
      "result": "Bestow",
      "resultTranslations": {
        "pt": "Conceder",
        "en": "Bestow"
      },
      "weight": 1,
      "entryRollOn": [],
      "tags": [],
      "disabled": false
    },
    {
      "range": [
        13,
        13
      ],
      "result": "Betrayal",
      "resultTranslations": {
        "pt": "Traição",
        "en": "Betrayal"
      },
      "weight": 1,
      "entryRollOn": [],
      "tags": [],
      "disabled": false
    },
    {
      "range": [
        14,
        14
      ],
      "result": "Bizarre",
      "resultTranslations": {
        "pt": "Bizarro",
        "en": "Bizarre"
      },
      "weight": 1,
      "entryRollOn": [],
      "tags": [],
      "disabled": false
    },
    {
      "range": [
        15,
        15
      ],
      "result": "Break",
      "resultTranslations": {
        "pt": "Quebrar",
        "en": "Break"
      },
      "weight": 1,
      "entryRollOn": [],
      "tags": [],
      "disabled": false
    },
    {
      "range": [
        16,
        16
      ],
      "result": "Calm",
      "resultTranslations": {
        "pt": "Calma",
        "en": "Calm"
      },
      "weight": 1,
      "entryRollOn": [],
      "tags": [],
      "disabled": false
    },
    {
      "range": [
        17,
        17
      ],
      "result": "Challenge",
      "resultTranslations": {
        "pt": "Desafio",
        "en": "Challenge"
      },
      "weight": 1,
      "entryRollOn": [],
      "tags": [],
      "disabled": false
    },
    {
      "range": [
        18,
        18
      ],
      "result": "Change",
      "resultTranslations": {
        "pt": "Mudar",
        "en": "Change"
      },
      "weight": 1,
      "entryRollOn": [],
      "tags": [],
      "disabled": false
    },
    {
      "range": [
        19,
        19
      ],
      "result": "Clue",
      "resultTranslations": {
        "pt": "Pista",
        "en": "Clue"
      },
      "weight": 1,
      "entryRollOn": [],
      "tags": [],
      "disabled": false
    },
    {
      "range": [
        20,
        20
      ],
      "result": "Communicate",
      "resultTranslations": {
        "pt": "Comunicar",
        "en": "Communicate"
      },
      "weight": 1,
      "entryRollOn": [],
      "tags": [],
      "disabled": false
    },
    {
      "range": [
        21,
        21
      ],
      "result": "Control",
      "resultTranslations": {
        "pt": "Controlar",
        "en": "Control"
      },
      "weight": 1,
      "entryRollOn": [],
      "tags": [],
      "disabled": false
    },
    {
      "range": [
        22,
        22
      ],
      "result": "Defense",
      "resultTranslations": {
        "pt": "Defesa",
        "en": "Defense"
      },
      "weight": 1,
      "entryRollOn": [],
      "tags": [],
      "disabled": false
    },
    {
      "range": [
        23,
        23
      ],
      "result": "Delay",
      "resultTranslations": {
        "pt": "Atrasar",
        "en": "Delay"
      },
      "weight": 1,
      "entryRollOn": [],
      "tags": [],
      "disabled": false
    },
    {
      "range": [
        24,
        24
      ],
      "result": "Deliverance",
      "resultTranslations": {
        "pt": "Salvação",
        "en": "Deliverance"
      },
      "weight": 1,
      "entryRollOn": [],
      "tags": [],
      "disabled": false
    },
    {
      "range": [
        25,
        25
      ],
      "result": "Desire",
      "resultTranslations": {
        "pt": "Desejo",
        "en": "Desire"
      },
      "weight": 1,
      "entryRollOn": [],
      "tags": [],
      "disabled": false
    },
    {
      "range": [
        26,
        26
      ],
      "result": "Disrupt",
      "resultTranslations": {
        "pt": "Interromper",
        "en": "Disrupt"
      },
      "weight": 1,
      "entryRollOn": [],
      "tags": [],
      "disabled": false
    },
    {
      "range": [
        27,
        27
      ],
      "result": "Energy",
      "resultTranslations": {
        "pt": "Energia",
        "en": "Energy"
      },
      "weight": 1,
      "entryRollOn": [],
      "tags": [],
      "disabled": false
    },
    {
      "range": [
        28,
        28
      ],
      "result": "Entrance",
      "resultTranslations": {
        "pt": "Entrada",
        "en": "Entrance"
      },
      "weight": 1,
      "entryRollOn": [],
      "tags": [],
      "disabled": false
    },
    {
      "range": [
        29,
        29
      ],
      "result": "Environment",
      "resultTranslations": {
        "pt": "Ambiente",
        "en": "Environment"
      },
      "weight": 1,
      "entryRollOn": [],
      "tags": [],
      "disabled": false
    },
    {
      "range": [
        30,
        30
      ],
      "result": "Equipment",
      "resultTranslations": {
        "pt": "Equipamento",
        "en": "Equipment"
      },
      "weight": 1,
      "entryRollOn": [],
      "tags": [],
      "disabled": false
    },
    {
      "range": [
        31,
        31
      ],
      "result": "Escape",
      "resultTranslations": {
        "pt": "Escapar",
        "en": "Escape"
      },
      "weight": 1,
      "entryRollOn": [],
      "tags": [],
      "disabled": false
    },
    {
      "range": [
        32,
        32
      ],
      "result": "Exit",
      "resultTranslations": {
        "pt": "Saída",
        "en": "Exit"
      },
      "weight": 1,
      "entryRollOn": [],
      "tags": [],
      "disabled": false
    },
    {
      "range": [
        33,
        33
      ],
      "result": "Expectation",
      "resultTranslations": {
        "pt": "Expectativa",
        "en": "Expectation"
      },
      "weight": 1,
      "entryRollOn": [],
      "tags": [],
      "disabled": false
    },
    {
      "range": [
        34,
        34
      ],
      "result": "Free",
      "resultTranslations": {
        "pt": "Libertar",
        "en": "Free"
      },
      "weight": 1,
      "entryRollOn": [],
      "tags": [],
      "disabled": false
    },
    {
      "range": [
        35,
        35
      ],
      "result": "Friendship",
      "resultTranslations": {
        "pt": "Amizade ",
        "en": "Friendship"
      },
      "weight": 1,
      "entryRollOn": [],
      "tags": [],
      "disabled": false
    },
    {
      "range": [
        36,
        36
      ],
      "result": "Gift",
      "resultTranslations": {
        "pt": "Dom",
        "en": "Gift"
      },
      "weight": 1,
      "entryRollOn": [],
      "tags": [],
      "disabled": false
    },
    {
      "range": [
        37,
        37
      ],
      "result": "Goal",
      "resultTranslations": {
        "pt": "Meta",
        "en": "Goal"
      },
      "weight": 1,
      "entryRollOn": [],
      "tags": [],
      "disabled": false
    },
    {
      "range": [
        38,
        38
      ],
      "result": "Good",
      "resultTranslations": {
        "pt": "Bem",
        "en": "Good"
      },
      "weight": 1,
      "entryRollOn": [],
      "tags": [],
      "disabled": false
    },
    {
      "range": [
        39,
        39
      ],
      "result": "Gratify",
      "resultTranslations": {
        "pt": "Gratificar",
        "en": "Gratify"
      },
      "weight": 1,
      "entryRollOn": [],
      "tags": [],
      "disabled": false
    },
    {
      "range": [
        40,
        40
      ],
      "result": "Guide",
      "resultTranslations": {
        "pt": "Guiar",
        "en": "Guide"
      },
      "weight": 1,
      "entryRollOn": [],
      "tags": [],
      "disabled": false
    },
    {
      "range": [
        41,
        41
      ],
      "result": "Help",
      "resultTranslations": {
        "pt": "Ajudar",
        "en": "Help"
      },
      "weight": 1,
      "entryRollOn": [],
      "tags": [],
      "disabled": false
    },
    {
      "range": [
        42,
        42
      ],
      "result": "Hidden",
      "resultTranslations": {
        "pt": "Escondido",
        "en": "Hidden"
      },
      "weight": 1,
      "entryRollOn": [],
      "tags": [],
      "disabled": false
    },
    {
      "range": [
        43,
        43
      ],
      "result": "Hope",
      "resultTranslations": {
        "pt": "Esperança",
        "en": "Hope"
      },
      "weight": 1,
      "entryRollOn": [],
      "tags": [],
      "disabled": false
    },
    {
      "range": [
        44,
        44
      ],
      "result": "Ideas",
      "resultTranslations": {
        "pt": "Ideias",
        "en": "Ideas"
      },
      "weight": 1,
      "entryRollOn": [],
      "tags": [],
      "disabled": false
    },
    {
      "range": [
        45,
        45
      ],
      "result": "Important",
      "resultTranslations": {
        "pt": "Importante",
        "en": "Important"
      },
      "weight": 1,
      "entryRollOn": [],
      "tags": [],
      "disabled": false
    },
    {
      "range": [
        46,
        46
      ],
      "result": "Increase",
      "resultTranslations": {
        "pt": "Aumento",
        "en": "Increase"
      },
      "weight": 1,
      "entryRollOn": [],
      "tags": [],
      "disabled": false
    },
    {
      "range": [
        47,
        47
      ],
      "result": "Information",
      "resultTranslations": {
        "pt": "Informação",
        "en": "Information"
      },
      "weight": 1,
      "entryRollOn": [],
      "tags": [],
      "disabled": false
    },
    {
      "range": [
        48,
        48
      ],
      "result": "Joy",
      "resultTranslations": {
        "pt": "Alegria",
        "en": "Joy"
      },
      "weight": 1,
      "entryRollOn": [],
      "tags": [],
      "disabled": false
    },
    {
      "range": [
        49,
        49
      ],
      "result": "Key",
      "resultTranslations": {
        "pt": "Chave",
        "en": "Key"
      },
      "weight": 1,
      "entryRollOn": [],
      "tags": [],
      "disabled": false
    },
    {
      "range": [
        50,
        50
      ],
      "result": "Liberty",
      "resultTranslations": {
        "pt": "Liberdade",
        "en": "Liberty"
      },
      "weight": 1,
      "entryRollOn": [],
      "tags": [],
      "disabled": false
    },
    {
      "range": [
        51,
        51
      ],
      "result": "Meager",
      "resultTranslations": {
        "pt": "Insuficiente",
        "en": "Meager"
      },
      "weight": 1,
      "entryRollOn": [],
      "tags": [],
      "disabled": false
    },
    {
      "range": [
        52,
        52
      ],
      "result": "Mechanical",
      "resultTranslations": {
        "pt": "Mecânico",
        "en": "Mechanical"
      },
      "weight": 1,
      "entryRollOn": [],
      "tags": [],
      "disabled": false
    },
    {
      "range": [
        53,
        53
      ],
      "result": "Message",
      "resultTranslations": {
        "pt": "Mensagem",
        "en": "Message"
      },
      "weight": 1,
      "entryRollOn": [],
      "tags": [],
      "disabled": false
    },
    {
      "range": [
        54,
        54
      ],
      "result": "Move",
      "resultTranslations": {
        "pt": "Mover",
        "en": "Move"
      },
      "weight": 1,
      "entryRollOn": [],
      "tags": [],
      "disabled": false
    },
    {
      "range": [
        55,
        55
      ],
      "result": "Mundane",
      "resultTranslations": {
        "pt": "Mundano",
        "en": "Mundane"
      },
      "weight": 1,
      "entryRollOn": [],
      "tags": [],
      "disabled": false
    },
    {
      "range": [
        56,
        56
      ],
      "result": "Mysterious",
      "resultTranslations": {
        "pt": "Misterioso",
        "en": "Mysterious"
      },
      "weight": 1,
      "entryRollOn": [],
      "tags": [],
      "disabled": false
    },
    {
      "range": [
        57,
        57
      ],
      "result": "News",
      "resultTranslations": {
        "pt": "Notícias",
        "en": "News"
      },
      "weight": 1,
      "entryRollOn": [],
      "tags": [],
      "disabled": false
    },
    {
      "range": [
        58,
        58
      ],
      "result": "Normal",
      "resultTranslations": {
        "pt": "Normal",
        "en": "Normal"
      },
      "weight": 1,
      "entryRollOn": [],
      "tags": [],
      "disabled": false
    },
    {
      "range": [
        59,
        59
      ],
      "result": "Object",
      "resultTranslations": {
        "pt": "Objeto",
        "en": "Object"
      },
      "weight": 1,
      "entryRollOn": [],
      "tags": [],
      "disabled": false
    },
    {
      "range": [
        60,
        60
      ],
      "result": "Odd",
      "resultTranslations": {
        "pt": "Esquisito",
        "en": "Odd"
      },
      "weight": 1,
      "entryRollOn": [],
      "tags": [],
      "disabled": false
    },
    {
      "range": [
        61,
        61
      ],
      "result": "Official",
      "resultTranslations": {
        "pt": "Oficial",
        "en": "Official"
      },
      "weight": 1,
      "entryRollOn": [],
      "tags": [],
      "disabled": false
    },
    {
      "range": [
        62,
        62
      ],
      "result": "Open",
      "resultTranslations": {
        "pt": "Abrir",
        "en": "Open"
      },
      "weight": 1,
      "entryRollOn": [],
      "tags": [],
      "disabled": false
    },
    {
      "range": [
        63,
        63
      ],
      "result": "Outside",
      "resultTranslations": {
        "pt": "Fora",
        "en": "Outside"
      },
      "weight": 1,
      "entryRollOn": [],
      "tags": [],
      "disabled": false
    },
    {
      "range": [
        64,
        64
      ],
      "result": "Overthrow",
      "resultTranslations": {
        "pt": "Suplantar",
        "en": "Overthrow"
      },
      "weight": 1,
      "entryRollOn": [],
      "tags": [],
      "disabled": false
    },
    {
      "range": [
        65,
        65
      ],
      "result": "Partial",
      "resultTranslations": {
        "pt": "Parcial",
        "en": "Partial"
      },
      "weight": 1,
      "entryRollOn": [],
      "tags": [],
      "disabled": false
    },
    {
      "range": [
        66,
        66
      ],
      "result": "Path",
      "resultTranslations": {
        "pt": "Caminho",
        "en": "Path"
      },
      "weight": 1,
      "entryRollOn": [],
      "tags": [],
      "disabled": false
    },
    {
      "range": [
        67,
        67
      ],
      "result": "Peace",
      "resultTranslations": {
        "pt": "Paz",
        "en": "Peace"
      },
      "weight": 1,
      "entryRollOn": [],
      "tags": [],
      "disabled": false
    },
    {
      "range": [
        68,
        68
      ],
      "result": "Physical",
      "resultTranslations": {
        "pt": "Físico",
        "en": "Physical"
      },
      "weight": 1,
      "entryRollOn": [],
      "tags": [],
      "disabled": false
    },
    {
      "range": [
        69,
        69
      ],
      "result": "Portal",
      "resultTranslations": {
        "pt": "Portal",
        "en": "Portal"
      },
      "weight": 1,
      "entryRollOn": [],
      "tags": [],
      "disabled": false
    },
    {
      "range": [
        70,
        70
      ],
      "result": "Possessions",
      "resultTranslations": {
        "pt": "Posses",
        "en": "Possessions"
      },
      "weight": 1,
      "entryRollOn": [],
      "tags": [],
      "disabled": false
    },
    {
      "range": [
        71,
        71
      ],
      "result": "Postpone",
      "resultTranslations": {
        "pt": "Adiar",
        "en": "Postpone"
      },
      "weight": 1,
      "entryRollOn": [],
      "tags": [],
      "disabled": false
    },
    {
      "range": [
        72,
        72
      ],
      "result": "Power",
      "resultTranslations": {
        "pt": "Poder",
        "en": "Power"
      },
      "weight": 1,
      "entryRollOn": [],
      "tags": [],
      "disabled": false
    },
    {
      "range": [
        73,
        73
      ],
      "result": "Progress",
      "resultTranslations": {
        "pt": "Progresso",
        "en": "Progress"
      },
      "weight": 1,
      "entryRollOn": [],
      "tags": [],
      "disabled": false
    },
    {
      "range": [
        74,
        74
      ],
      "result": "Reassuring",
      "resultTranslations": {
        "pt": "Tranquilizador",
        "en": "Reassuring"
      },
      "weight": 1,
      "entryRollOn": [],
      "tags": [],
      "disabled": false
    },
    {
      "range": [
        75,
        75
      ],
      "result": "Release",
      "resultTranslations": {
        "pt": "Soltar",
        "en": "Release"
      },
      "weight": 1,
      "entryRollOn": [],
      "tags": [],
      "disabled": false
    },
    {
      "range": [
        76,
        76
      ],
      "result": "Replenish",
      "resultTranslations": {
        "pt": "Repor",
        "en": "Replenish"
      },
      "weight": 1,
      "entryRollOn": [],
      "tags": [],
      "disabled": false
    },
    {
      "range": [
        77,
        77
      ],
      "result": "Resolution",
      "resultTranslations": {
        "pt": "Resolução",
        "en": "Resolution"
      },
      "weight": 1,
      "entryRollOn": [],
      "tags": [],
      "disabled": false
    },
    {
      "range": [
        78,
        78
      ],
      "result": "Resource",
      "resultTranslations": {
        "pt": "Recurso",
        "en": "Resource"
      },
      "weight": 1,
      "entryRollOn": [],
      "tags": [],
      "disabled": false
    },
    {
      "range": [
        79,
        79
      ],
      "result": "Return",
      "resultTranslations": {
        "pt": "Retornar",
        "en": "Return"
      },
      "weight": 1,
      "entryRollOn": [],
      "tags": [],
      "disabled": false
    },
    {
      "range": [
        80,
        80
      ],
      "result": "Revealed",
      "resultTranslations": {
        "pt": "Revelação",
        "en": "Revealed"
      },
      "weight": 1,
      "entryRollOn": [],
      "tags": [],
      "disabled": false
    },
    {
      "range": [
        81,
        81
      ],
      "result": "Riches",
      "resultTranslations": {
        "pt": "Riquezas",
        "en": "Riches"
      },
      "weight": 1,
      "entryRollOn": [],
      "tags": [],
      "disabled": false
    },
    {
      "range": [
        82,
        82
      ],
      "result": "Safety",
      "resultTranslations": {
        "pt": "Segurança",
        "en": "Safety"
      },
      "weight": 1,
      "entryRollOn": [],
      "tags": [],
      "disabled": false
    },
    {
      "range": [
        83,
        83
      ],
      "result": "Simple",
      "resultTranslations": {
        "pt": "Simples",
        "en": "Simple"
      },
      "weight": 1,
      "entryRollOn": [],
      "tags": [],
      "disabled": false
    },
    {
      "range": [
        84,
        84
      ],
      "result": "Small",
      "resultTranslations": {
        "pt": "Pequeno",
        "en": "Small"
      },
      "weight": 1,
      "entryRollOn": [],
      "tags": [],
      "disabled": false
    },
    {
      "range": [
        85,
        85
      ],
      "result": "Start",
      "resultTranslations": {
        "pt": "Começar",
        "en": "Start"
      },
      "weight": 1,
      "entryRollOn": [],
      "tags": [],
      "disabled": false
    },
    {
      "range": [
        86,
        86
      ],
      "result": "Stop",
      "resultTranslations": {
        "pt": "Parar",
        "en": "Stop"
      },
      "weight": 1,
      "entryRollOn": [],
      "tags": [],
      "disabled": false
    },
    {
      "range": [
        87,
        87
      ],
      "result": "Strange",
      "resultTranslations": {
        "pt": "Estranho",
        "en": "Strange"
      },
      "weight": 1,
      "entryRollOn": [],
      "tags": [],
      "disabled": false
    },
    {
      "range": [
        88,
        88
      ],
      "result": "Success",
      "resultTranslations": {
        "pt": "Sucesso",
        "en": "Success"
      },
      "weight": 1,
      "entryRollOn": [],
      "tags": [],
      "disabled": false
    },
    {
      "range": [
        89,
        89
      ],
      "result": "Task",
      "resultTranslations": {
        "pt": "Tarefa",
        "en": "Task"
      },
      "weight": 1,
      "entryRollOn": [],
      "tags": [],
      "disabled": false
    },
    {
      "range": [
        90,
        90
      ],
      "result": "Tool",
      "resultTranslations": {
        "pt": "Ferramenta",
        "en": "Tool"
      },
      "weight": 1,
      "entryRollOn": [],
      "tags": [],
      "disabled": false
    },
    {
      "range": [
        91,
        91
      ],
      "result": "Transform",
      "resultTranslations": {
        "pt": "Transformar",
        "en": "Transform"
      },
      "weight": 1,
      "entryRollOn": [],
      "tags": [],
      "disabled": false
    },
    {
      "range": [
        92,
        92
      ],
      "result": "Trap",
      "resultTranslations": {
        "pt": "Armadilha",
        "en": "Trap"
      },
      "weight": 1,
      "entryRollOn": [],
      "tags": [],
      "disabled": false
    },
    {
      "range": [
        93,
        93
      ],
      "result": "Travel",
      "resultTranslations": {
        "pt": "Viajar",
        "en": "Travel"
      },
      "weight": 1,
      "entryRollOn": [],
      "tags": [],
      "disabled": false
    },
    {
      "range": [
        94,
        94
      ],
      "result": "Treasure",
      "resultTranslations": {
        "pt": "Tesouro",
        "en": "Treasure"
      },
      "weight": 1,
      "entryRollOn": [],
      "tags": [],
      "disabled": false
    },
    {
      "range": [
        95,
        95
      ],
      "result": "Triumph",
      "resultTranslations": {
        "pt": "Triunfo",
        "en": "Triumph"
      },
      "weight": 1,
      "entryRollOn": [],
      "tags": [],
      "disabled": false
    },
    {
      "range": [
        96,
        96
      ],
      "result": "Truce",
      "resultTranslations": {
        "pt": "Trégua",
        "en": "Truce"
      },
      "weight": 1,
      "entryRollOn": [],
      "tags": [],
      "disabled": false
    },
    {
      "range": [
        97,
        97
      ],
      "result": "Valuable",
      "resultTranslations": {
        "pt": "Valioso",
        "en": "Valuable"
      },
      "weight": 1,
      "entryRollOn": [],
      "tags": [],
      "disabled": false
    },
    {
      "range": [
        98,
        98
      ],
      "result": "Victory",
      "resultTranslations": {
        "pt": "Vitória",
        "en": "Victory"
      },
      "weight": 1,
      "entryRollOn": [],
      "tags": [],
      "disabled": false
    },
    {
      "range": [
        99,
        99
      ],
      "result": "Weapon",
      "resultTranslations": {
        "pt": "Arma",
        "en": "Weapon"
      },
      "weight": 1,
      "entryRollOn": [],
      "tags": [],
      "disabled": false
    },
    {
      "range": [
        100,
        100
      ],
      "result": "Wishes",
      "resultTranslations": {
        "pt": "Desejos",
        "en": "Wishes"
      },
      "weight": 1,
      "entryRollOn": [],
      "tags": [],
      "disabled": false
    }
  ],
  "rangeStart": 1,
  "rangeEnd": 100,
  "tableRollOn": [],
  "replacement": false,
  "displayRoll": true
}
